[{"path":"src/main/java/Freedom.java","fileType":"java","lines":[{"lineNumber":1,"author":{"gitId":"Ridiculouswifi"},"content":"import java.util.Scanner;","lastModifiedDate":"2024-08-29","isFullCredit":false},{"lineNumber":2,"author":{"gitId":"Ridiculouswifi"},"content":"import java.util.Arrays;","lastModifiedDate":"2024-08-29","isFullCredit":false},{"lineNumber":3,"author":{"gitId":"Ridiculouswifi"},"content":"","lastModifiedDate":"2024-08-29","isFullCredit":false},{"lineNumber":4,"author":{"gitId":"Ridiculouswifi"},"content":"public class Freedom {","lastModifiedDate":"2024-08-28","isFullCredit":false},{"lineNumber":5,"author":{"gitId":"Ridiculouswifi"},"content":"    public static void main(String[] args) {","lastModifiedDate":"2024-08-28","isFullCredit":false},{"lineNumber":6,"author":{"gitId":"Ridiculouswifi"},"content":"        String[] storage \u003d new String[100];","lastModifiedDate":"2024-08-29","isFullCredit":false},{"lineNumber":7,"author":{"gitId":"Ridiculouswifi"},"content":"        int lastIndex \u003d 0;","lastModifiedDate":"2024-08-29","isFullCredit":false},{"lineNumber":8,"author":{"gitId":"Ridiculouswifi"},"content":"        String logo \u003d \"\\t_________________________________________\\n\";","lastModifiedDate":"2024-08-29","isFullCredit":false},{"lineNumber":9,"author":{"gitId":"Ridiculouswifi"},"content":"        String message \u003d \"\"\"","lastModifiedDate":"2024-08-28","isFullCredit":false},{"lineNumber":10,"author":{"gitId":"Ridiculouswifi"},"content":"                \\tHello! I\u0027m Freedom","lastModifiedDate":"2024-08-29","isFullCredit":false},{"lineNumber":11,"author":{"gitId":"Ridiculouswifi"},"content":"                \\tWhat can I do for you?","lastModifiedDate":"2024-08-29","isFullCredit":false},{"lineNumber":12,"author":{"gitId":"Ridiculouswifi"},"content":"                \"\"\";","lastModifiedDate":"2024-08-28","isFullCredit":false},{"lineNumber":13,"author":{"gitId":"Ridiculouswifi"},"content":"        String closing \u003d \"\\tBye. Hope to see you again soon!\\n\";","lastModifiedDate":"2024-08-29","isFullCredit":false},{"lineNumber":14,"author":{"gitId":"Ridiculouswifi"},"content":"","lastModifiedDate":"2024-08-29","isFullCredit":false},{"lineNumber":15,"author":{"gitId":"Ridiculouswifi"},"content":"        System.out.println(logo + message + logo);","lastModifiedDate":"2024-08-29","isFullCredit":false},{"lineNumber":16,"author":{"gitId":"Ridiculouswifi"},"content":"","lastModifiedDate":"2024-08-29","isFullCredit":false},{"lineNumber":17,"author":{"gitId":"Ridiculouswifi"},"content":"        while (true) {","lastModifiedDate":"2024-08-29","isFullCredit":false},{"lineNumber":18,"author":{"gitId":"Ridiculouswifi"},"content":"            Scanner in \u003d new Scanner(System.in);","lastModifiedDate":"2024-08-29","isFullCredit":false},{"lineNumber":19,"author":{"gitId":"Ridiculouswifi"},"content":"            String line \u003d in.nextLine();","lastModifiedDate":"2024-08-29","isFullCredit":false},{"lineNumber":20,"author":{"gitId":"Ridiculouswifi"},"content":"","lastModifiedDate":"2024-08-29","isFullCredit":false},{"lineNumber":21,"author":{"gitId":"Ridiculouswifi"},"content":"            if (line.equals(\"bye\")) {","lastModifiedDate":"2024-08-29","isFullCredit":false},{"lineNumber":22,"author":{"gitId":"Ridiculouswifi"},"content":"                break;","lastModifiedDate":"2024-08-29","isFullCredit":false},{"lineNumber":23,"author":{"gitId":"Ridiculouswifi"},"content":"            }","lastModifiedDate":"2024-08-29","isFullCredit":false},{"lineNumber":24,"author":{"gitId":"Ridiculouswifi"},"content":"            handleInput(line, storage, lastIndex);","lastModifiedDate":"2024-08-29","isFullCredit":false},{"lineNumber":25,"author":{"gitId":"Ridiculouswifi"},"content":"            if (!line.equals(\"list\")) {","lastModifiedDate":"2024-08-29","isFullCredit":false},{"lineNumber":26,"author":{"gitId":"Ridiculouswifi"},"content":"                lastIndex++;","lastModifiedDate":"2024-08-29","isFullCredit":false},{"lineNumber":27,"author":{"gitId":"Ridiculouswifi"},"content":"            }","lastModifiedDate":"2024-08-29","isFullCredit":false},{"lineNumber":28,"author":{"gitId":"Ridiculouswifi"},"content":"        }","lastModifiedDate":"2024-08-29","isFullCredit":false},{"lineNumber":29,"author":{"gitId":"Ridiculouswifi"},"content":"","lastModifiedDate":"2024-08-29","isFullCredit":false},{"lineNumber":30,"author":{"gitId":"Ridiculouswifi"},"content":"        System.out.println(logo + closing + logo);","lastModifiedDate":"2024-08-29","isFullCredit":false},{"lineNumber":31,"author":{"gitId":"Ridiculouswifi"},"content":"    }","lastModifiedDate":"2024-08-28","isFullCredit":false},{"lineNumber":32,"author":{"gitId":"Ridiculouswifi"},"content":"","lastModifiedDate":"2024-08-29","isFullCredit":false},{"lineNumber":33,"author":{"gitId":"Ridiculouswifi"},"content":"    public static void handleInput(String input, String[] storage, int lastIndex) {","lastModifiedDate":"2024-08-29","isFullCredit":false},{"lineNumber":34,"author":{"gitId":"Ridiculouswifi"},"content":"        if (input.equals(\"list\")) {","lastModifiedDate":"2024-08-29","isFullCredit":false},{"lineNumber":35,"author":{"gitId":"Ridiculouswifi"},"content":"            printList(Arrays.copyOf(storage, lastIndex));","lastModifiedDate":"2024-08-29","isFullCredit":false},{"lineNumber":36,"author":{"gitId":"Ridiculouswifi"},"content":"            return;","lastModifiedDate":"2024-08-29","isFullCredit":false},{"lineNumber":37,"author":{"gitId":"Ridiculouswifi"},"content":"        }","lastModifiedDate":"2024-08-29","isFullCredit":false},{"lineNumber":38,"author":{"gitId":"Ridiculouswifi"},"content":"        storage[lastIndex] \u003d input;","lastModifiedDate":"2024-08-29","isFullCredit":false},{"lineNumber":39,"author":{"gitId":"Ridiculouswifi"},"content":"        String logo \u003d \"\\t_________________________________________\\n\";","lastModifiedDate":"2024-08-29","isFullCredit":false},{"lineNumber":40,"author":{"gitId":"Ridiculouswifi"},"content":"        System.out.println(logo + \"\\tadded: \" + input + \"\\n\" + logo);","lastModifiedDate":"2024-08-29","isFullCredit":false},{"lineNumber":41,"author":{"gitId":"Ridiculouswifi"},"content":"    }","lastModifiedDate":"2024-08-29","isFullCredit":false},{"lineNumber":42,"author":{"gitId":"Ridiculouswifi"},"content":"","lastModifiedDate":"2024-08-29","isFullCredit":false},{"lineNumber":43,"author":{"gitId":"Ridiculouswifi"},"content":"    public static void printList(String[] storage) {","lastModifiedDate":"2024-08-29","isFullCredit":false},{"lineNumber":44,"author":{"gitId":"Ridiculouswifi"},"content":"        String logo \u003d \"\\t_________________________________________\\n\";","lastModifiedDate":"2024-08-29","isFullCredit":false},{"lineNumber":45,"author":{"gitId":"Ridiculouswifi"},"content":"        int counter \u003d 0;","lastModifiedDate":"2024-08-29","isFullCredit":false},{"lineNumber":46,"author":{"gitId":"Ridiculouswifi"},"content":"        System.out.print(logo);","lastModifiedDate":"2024-08-29","isFullCredit":false},{"lineNumber":47,"author":{"gitId":"Ridiculouswifi"},"content":"        for (String item: storage) {","lastModifiedDate":"2024-08-29","isFullCredit":false},{"lineNumber":48,"author":{"gitId":"Ridiculouswifi"},"content":"            System.out.println(\"\\t\" + (counter + 1) + \". \" + item);","lastModifiedDate":"2024-08-29","isFullCredit":false},{"lineNumber":49,"author":{"gitId":"Ridiculouswifi"},"content":"            counter++;","lastModifiedDate":"2024-08-29","isFullCredit":false},{"lineNumber":50,"author":{"gitId":"Ridiculouswifi"},"content":"        }","lastModifiedDate":"2024-08-29","isFullCredit":false},{"lineNumber":51,"author":{"gitId":"Ridiculouswifi"},"content":"        System.out.print(logo);","lastModifiedDate":"2024-08-29","isFullCredit":false},{"lineNumber":52,"author":{"gitId":"Ridiculouswifi"},"content":"    }","lastModifiedDate":"2024-08-29","isFullCredit":false},{"lineNumber":53,"author":{"gitId":"Ridiculouswifi"},"content":"}","lastModifiedDate":"2024-08-28","isFullCredit":false}],"authorContributionMap":{"Ridiculouswifi":53}}]
