{"authorDailyContributionsMap":{"paulktham":[{"date":"2024-08-21","commitResults":[{"hash":"c1037daab0d828117e0cc3ae902d1d08c1f0d3bb","isMergeCommit":false,"messageTitle":"Level-0-a","messageBody":"","fileTypesAndContributionMap":{"java":{"insertions":15,"deletions":0}}},{"hash":"3b4fe69c95b2de08ddaa9cd307ff7ea441989a6e","isMergeCommit":false,"messageTitle":"Level-0-b","messageBody":"","fileTypesAndContributionMap":{"java":{"insertions":0,"deletions":10}}}]},{"date":"2024-08-26","commitResults":[{"hash":"22faae3215db92299cdf57016165ccd1b1e7d769","isMergeCommit":false,"messageTitle":"Level-1","messageBody":"","fileTypesAndContributionMap":{"java":{"insertions":20,"deletions":6}}}]},{"date":"2024-08-28","commitResults":[{"hash":"db2344bd741af8188b4efebfad16d7d10e93e561","isMergeCommit":false,"messageTitle":"level 2","messageBody":"","fileTypesAndContributionMap":{"java":{"insertions":28,"deletions":10}}},{"hash":"d5eb7883c7b0c157853c4a5f57e2e701ba5b36f4","isMergeCommit":false,"messageTitle":"Level 3.1","messageBody":"","fileTypesAndContributionMap":{"java":{"insertions":34,"deletions":2}}}]},{"date":"2024-09-05","commitResults":[{"hash":"c8cc74682fc6a3d6737188c3496a654511bb779b","isMergeCommit":false,"messageTitle":"Level-4","messageBody":"","fileTypesAndContributionMap":{"txt":{"insertions":1,"deletions":0},"java":{"insertions":166,"deletions":68},"bat":{"insertions":2,"deletions":2}}}]},{"date":"2024-09-09","commitResults":[{"hash":"05e4753ad8c9b3fba6dd39366281eec364dc30cd","isMergeCommit":false,"messageTitle":"exception handling","messageBody":"","fileTypesAndContributionMap":{"java":{"insertions":73,"deletions":6}}}]},{"date":"2024-09-11","commitResults":[{"hash":"3d8be8034f5ddf7ff669b154dc5cf0636b27abc1","isMergeCommit":false,"messageTitle":"package control","messageBody":"","fileTypesAndContributionMap":{"java":{"insertions":87,"deletions":95}}}]},{"date":"2024-09-16","commitResults":[{"hash":"88f05d45d90125b683c7d0795e34f555c8d04c0b","isMergeCommit":false,"messageTitle":"delete function and arraylist","messageBody":"","fileTypesAndContributionMap":{"java":{"insertions":119,"deletions":22}}},{"hash":"c53d15fff2383c4e9b14b5e5a29495c511735b9a","isMergeCommit":false,"messageTitle":"save function","messageBody":"","fileTypesAndContributionMap":{"java":{"insertions":70,"deletions":0}}},{"hash":"2509408b4100f2309cae664bee6e972bbf468d12","isMergeCommit":false,"messageTitle":"fix bugs from level 6","messageBody":"","fileTypesAndContributionMap":{"java":{"insertions":34,"deletions":15}}},{"hash":"0bf10264b7abb403c25045706f5fcbbb13ee6c9e","isMergeCommit":true,"messageTitle":"Merge branch \u0027branch-level-7\u0027 and fix bugs","messageBody":"","tags":["release"],"fileTypesAndContributionMap":{}}]},{"date":"2024-09-27","commitResults":[{"hash":"a7bf5e108e8a9855e18d1f6921009e590a3b0d20","isMergeCommit":false,"messageTitle":"A-MoreOOP","messageBody":"","fileTypesAndContributionMap":{"java":{"insertions":278,"deletions":118}}}]},{"date":"2024-09-28","commitResults":[{"hash":"2591f717ef4f7870e693c37bec43a9abba42c266","isMergeCommit":false,"messageTitle":"A-MoreOOP-V2","messageBody":"","fileTypesAndContributionMap":{"java":{"insertions":194,"deletions":113}}},{"hash":"6fb3fadebc02ecaa5e40cb3d2104e8293de7e0bc","isMergeCommit":true,"messageTitle":"Merge branch \u0027master\u0027 of https://github.com/paulktham/ip","messageBody":"","fileTypesAndContributionMap":{}}]}]},"authorFileTypeContributionMap":{"paulktham":{"java":486,"md":0,"fxml":0,"sh":0,"bat":1,"gradle":0,"txt":1}},"authorContributionVariance":{"paulktham":8286.717},"authorDisplayNameMap":{"paulktham":"CS2113-W12-2 PAUL..G LE"}}
