{"authorDailyContributionsMap":{"Oshen27":[{"date":"2024-08-28","commitResults":[{"hash":"15810c5f67cb8a29846f6417aed9a6c4845eb34a","isMergeCommit":false,"messageTitle":"Rename, Greet, Exit","messageBody":"","tags":["Level-0"],"fileTypesAndContributionMap":{"java":{"insertions":12,"deletions":10}}},{"hash":"9244e7fc4346a1897882b0c389abb91025624436","isMergeCommit":true,"messageTitle":"Merge commit \u002781a9c537afe8492675eb253968939364d65db091\u0027","messageBody":"","fileTypesAndContributionMap":{}}]},{"date":"2024-08-29","commitResults":[{"hash":"6fe4a3492ddf3812149d4f683c5972c9d2ee3e29","isMergeCommit":false,"messageTitle":"Echo and Add List","messageBody":"","tags":["Level-2","Level-1"],"fileTypesAndContributionMap":{"java":{"insertions":25,"deletions":1}}},{"hash":"d60d028c3abae8b9e680c7ab4f1d951fefe20257","isMergeCommit":false,"messageTitle":"Implemented Mark As Done feature","messageBody":"Added Task Class\n","tags":["Level-3"],"fileTypesAndContributionMap":{"java":{"insertions":53,"deletions":8}}},{"hash":"b113c3742a51e605bd0730fe32a12993f3183d2e","isMergeCommit":false,"messageTitle":"Tweaked code to comply with coding standard","messageBody":"","tags":["A-CodingStandard"],"fileTypesAndContributionMap":{"java":{"insertions":4,"deletions":6}}}]}]},"authorFileTypeContributionMap":{"Oshen27":{"java":79,"md":0,"fxml":0,"sh":0,"bat":0,"gradle":0,"txt":0}},"authorContributionVariance":{"Oshen27":634.3929},"authorDisplayNameMap":{"Oshen27":"SHEN..MING"}}
